{
  "$schema": "https://raw.githubusercontent.com/victorfrye/microsoftgraveyard/main/files/corpses.schema.json",
  "corpses": [
    {
      "name": "Azure Blueprints",
      "birthDate": "2018-09-01",
      "deathDate": "2026-07-11",
      "description": "a declarative way to orchestrate the deployment of various resource templates, policies, role assignments, and other artifacts",
      "link": "https://www.pluralsight.com/resources/blog/cloud/azure-blueprints-shelved"
    },
    {
      "name": "Windows 10",
      "birthDate": "2015-07-15",
      "deathDate": "2025-11-14",
      "description": "a major release of the Windows NT operating system succeeding Windows 8.1",
      "link": "https://en.wikipedia.org/wiki/Windows_10"
    },
    {
      "name": "Teams Live Events",
      "birthDate": "2019-03-26",
      "deathDate": "2024-09-30",
      "description": "a feature of Teams that allowed users to broadcast live, on-demand video events up to 10k attendees",
      "link": "https://learn.microsoft.com/en-us/microsoftteams/teams-live-events/plan-for-teams-live-events"
    },
    {
      "name": "Visual Studio for Mac",
      "birthDate": "1905-07-08",
      "deathDate": "2024-08-31",
      "description": "a Mac-specific integrated development environment for projects using Mono or the .NET cross-platform framework",
      "link": "https://www.bleepingcomputer.com/news/software/microsoft-retires-visual-studio-for-mac-support-ends-in-a-year/"
    },
    {
      "name": "Xbox 360 Store",
      "birthDate": "2005-11-22",
      "deathDate": "2024-07-29",
      "description": "a marketplace for digital games released on the Xbox 360 console",
      "link": "https://support.xbox.com/en-US/help/xbox-360/store/xbox-360-marketplace-update"
    },
    {
      "name": "Xamarin",
      "birthDate": "2011-05-16",
      "deathDate": "2024-05-01",
      "description": "a cross-platform app development tool and framework that extended the .NET ecosystem",
      "link": "https://diversido.io/blog/xamarin-is-being-discontinued-what-does-it-mean-for-developers"
    },
    {
      "name": "Odyssey",
      "deathDate": "2024-01-25",
      "description": "an unreleased survival game that was in development by Blizzard and cancelled after the acquisition of Activision Blizzard by Microsoft",
      "link": "https://www.msn.com/en-us/entertainment/gaming/blizzard-cancels-survival-game-following-layoffs/ar-BB1hftuk"
    },
    {
      "name": "Windows Mixed Reality",
      "birthDate": "2016-10-01",
      "deathDate": "2023-12-21",
      "description": "an augmented and virtual reality platform for compatible Windows headsets",
      "link": "https://www.theverge.com/2023/12/21/24010787/microsoft-windows-mixed-reality-deprecated"
    },
    {
      "name": "VBScript",
      "birthDate": "1996-08-01",
      "deathDate": "2023-10-01",
      "description": "an Active Scripting language modeled on Visual Basic",
      "link": "https://en.wikipedia.org/wiki/VBScript"
    },
    {
      "name": "Xbox Live Gold",
      "birthDate": "2002-11-15",
      "deathDate": "2023-09-14",
      "description": "a gaming subscription service that enabled console multiplayer services",
      "link": "https://www.theverge.com/2023/7/17/23794792/microsoft-xbox-game-pass-core-live-gold-replacement"
    },
    {
      "name": "Surface Duo",
      "birthDate": "2020-09-10",
      "deathDate": "2023-09-10",
      "description": "a line of dual-screen Android devices that acted as Microsoft's re-entry into the mobile device market",
      "link": "https://arstechnica.com/gadgets/2023/01/rip-surface-duo-microsoft-reportedly-gives-up-on-the-weird-form-factor/"
    },
    {
      "name": "WordPad",
      "birthDate": "1995-08-24",
      "deathDate": "2023-09-01",
      "description": "a basic word processor software with rich text editing",
      "link": "https://www.msn.com/en-us/news/technology/microsoft-is-saying-goodbye-to-wordpad-forever/ar-AA1muYal"
    },
    {
      "name": "Cortana",
      "birthDate": "2014-04-02",
      "deathDate": "2023-08-31",
      "description": "a virtual assistant that used Bing search engine to perform tasks",
      "link": "https://www.theverge.com/2023/8/11/23828311/microsoft-shuts-down-cortana-windows-11"
    },
    {
      "name": "Kaizala",
      "birthDate": "2019-06-29",
      "deathDate": "2023-08-31",
      "description": "a secure messaging and workplace productivity application for collaboration",
      "link": "https://www.zdnet.com/article/microsoft-to-drop-its-kaizala-group-messaging-service-in-2023/"
    },
    {
      "name": "Kinect",
      "birthDate": "2010-11-04",
      "deathDate": "2023-08-17",
      "description": "a motion sensing input device originally launched as a gaming peripheral and later acted as a development tool for machine learning, visual recognition, and robotics",
      "link": "https://techcrunch.com/2023/08/22/microsoft-cant-stop-discontinuing-kinect/"
    },
    {
      "name": "Yammer",
      "birthDate": "2008-09-08",
      "deathDate": "2023-06-30",
      "description": "an enterprise social networking service primarily used for private communication within organizations that was acquired by Microsoft in 2012",
      "link": "https://www.zdnet.com/home-and-office/work-life/microsoft-say-goodbye-to-yammer-brand-hello-to-viva-engage/"
    },
    {
      "name": "Windows 8.1",
      "birthDate": "2013-11-13",
      "deathDate": "2023-01-10",
      "description": "a release of the Windows NT operating system succeeding Windows 8 with an improved Start screen",
      "link": "https://en.wikipedia.org/wiki/Windows_8.1"
    },
    {
      "name": "Atom",
      "birthDate": "2015-06-25",
      "deathDate": "2022-12-14",
      "description": "a free, cross-platform, open-source text and source code editor developed by GitHub",
      "link": "https://github.blog/2022-06-08-sunsetting-atom/"
    },
    {
      "name": "Internet Explorer",
      "birthDate": "1995-08-24",
      "deathDate": "2022-06-15",
      "description": "a web browser that once attained a peak 95% usage share",
      "link": "https://www.theverge.com/2021/5/19/22443997/microsoft-internet-explorer-end-of-support-date"
    },
    {
      "name": "JScript",
      "birthDate": "1996-08-01",
      "deathDate": "2022-06-15",
      "description": "a dialect of the ECMAScript standard used by Internet Explorer",
      "link": "https://www.theverge.com/2021/5/19/22443997/microsoft-internet-explorer-end-of-support-date"
    },
    {
      "name": "Trident",
      "birthDate": "1995-08-24",
      "deathDate": "2022-06-15",
      "description": "a proprietary browser engine (aka MSHTML) for Internet Explorer and IE mode of Edge",
      "link": "https://en.wikipedia.org/wiki/Trident_(software)"
    },
    {
      "name": "Forza Street",
      "birthDate": "2018-05-08",
      "deathDate": "2022-04-11",
      "description": "a free-to-play racing game developed by Electric Square and initially released as Miami Street on Windows PCs before rebranding and launching on mobile devices",
      "link": "https://comicbook.com/gaming/news/forza-street-game-shutting-down/"
    },
    {
      "name": "Channel 9",
      "birthDate": "2004-04-01",
      "deathDate": "2021-12-01",
      "description": "a website for hosting videos and podcasts that Microsoft employees created and the company's first blob",
      "link": "https://www.windowscentral.com/microsoft-learn-absorbs-channel-9-and-commits-preserving-its-essence"
    },
    {
      "name": "Silverlight",
      "birthDate": "2007-09-05",
      "deathDate": "2021-10-12",
      "description": "an application framework for writing and running web applications",
      "link": "https://support.microsoft.com/en-us/windows/silverlight-end-of-support-0a3be3c7-bead-e203-2dfd-74f0a64f1788"
    },
    {
      "name": "Skype for Business",
      "qualifier": "fka Lync",
      "birthDate": "2007-07-28",
      "deathDate": "2021-07-31",
      "description": "an enterprise software application for instant messaging and videotelephony",
      "link": "https://www.theverge.com/2017/9/25/16360072/microsoft-teams-replacing-skype-for-business"
    },
    {
      "name": "Xbox SmartGlass",
      "birthDate": "2012-06-05",
      "deathDate": "2021-06-30",
      "description": "a companion application to provide supplement content while playing games on Xbox devices",
      "link": "https://mspoweruser.com/microsoft-killing-xbox-one-smartglass-app-windows-pcs/#:~:text=Microsoft%20today%20announced%20that%20Xbox%20One%20SmartGlass%20app,who%20already%20downloaded%20the%20app%20to%20their%20devices."
    },
    {
      "name": "Gears POP!",
      "birthDate": "2019-08-22",
      "deathDate": "2021-04-26",
      "description": "a mobile real-time strategy game in which two players battle using Funko POP! stylized characters",
      "link": "https://www.destructoid.com/gears-pop-will-shut-down-its-servers-in-april-2021/"
    },
    {
      "name": "Flight Arcade",
      "birthDate": "2015-05-01",
      "deathDate": "2021-04-17",
      "description": "a free-to-play flight simulator and demonstration of how modern browsers handle high-end 3D graphics",
      "link": "https://www.windowscentral.com/microsoft-revisits-its-flight-simulator-series-web-based-flight-arcade-game"
    },
    {
      "name": "EdgeHTML",
      "birthDate": "2015-07-15",
      "deathDate": "2021-03-09",
      "description": "a proprietary browser engine used in Edge before being replaced by the Chromium-based version of Edge",
      "link": "https://www.reddit.com/r/firefox/comments/a2wfx8/gecko_is_the_last_engine_standing_microsoft_is/"
    },
    {
      "name": "Visual Studio Codespaces",
      "qualifier": "fka Visual Studio Online",
      "birthDate": "2019-11-04",
      "deathDate": "2021-02-17",
      "description": "a service providing cloud-hosted development environments",
      "link": "https://mspoweruser.com/microsoft-is-killing-visual-studio-codespaces/"
    },
    {
      "name": "Bleeding Edge",
      "birthDate": "2020-03-24",
      "deathDate": "2021-01-28",
      "description": "a multiplayer online battle arena game developed by Ninja Theory",
      "link": "https://www.polygon.com/2021/1/28/22254694/bleeding-edge-ended-development-shut-down-ninja-theory"
    },
    {
      "name": "Xbox One",
      "birthDate": "2013-11-22",
      "deathDate": "2020-12-31",
      "description": "the third gaming console from Microsoft and competed closely with the PlayStation 4",
      "link": "https://www.theverge.com/2022/1/13/22881211/microsoft-discontinues-xbox-one-consoles-2020"
    },
    {
      "name": "Mixer",
      "birthDate": "2016-01-05",
      "deathDate": "2020-07-22",
      "description": "a gaming streaming platform that allowed viewers to interact with and watch streamers",
      "link": "https://www.theverge.com/2020/6/22/21299032/microsoft-mixer-closing-facebook-gaming-partnership-xcloud-features"
    },
    {
      "name": "Wunderlist",
      "birthDate": "2010-11-09",
      "deathDate": "2020-05-06",
      "description": "a task management application that allowed users to creat lists of and manage tasks across devices",
      "link": "https://techcrunch.com/2019/12/09/microsoft-to-finally-shut-down-to-do-list-app-wunderlist-on-may-6-2020/"
    },
    {
      "name": "Windows 7",
      "birthDate": "2009-07-22",
      "deathDate": "2020-01-14",
      "description": "a major release of the Windows NT operating system succeeding and improving on Windows Vista",
      "link": "whttps://en.wikipedia.org/wiki/Windows_7"
    },
    {
      "name": "Windows Phone",
      "birthDate": "2010-10-21",
      "deathDate": "2020-01-14",
      "description": "a family of mobile operating systems that succeeded Windows Mobile and Zune before being discontinued",
      "link": "https://www.cnet.com/tech/mobile/windows-10-mobile-features-hardware-death-sentence-microsoft/"
    },
    {
      "name": "HealthVault",
      "birthDate": "2007-10-04",
      "deathDate": "2019-11-20",
      "description": "a web-based personal health record to store and maintain health and fitness information",
      "link": "https://www.zdnet.com/article/microsoft-is-closing-its-healthvault-patient-records-service-on-november-20/"
    },
    {
      "name": "Excel Viewer",
      "birthDate": "1997-02-27",
      "deathDate": "2018-04-30",
      "description": "a freeware program for Windows that can display and print Microsoft Excel spreadsheets",
      "link": "https://en.wikipedia.org/wiki/Microsoft_Excel#Microsoft_Excel_Viewer"
    },
    {
      "name": "PowerPoint Viewer",
      "birthDate": "1992-08-01",
      "deathDate": "2018-04-30",
      "description": "a freeware program for Windows that can display and print Microsoft PowerPoint presentations",
      "link": "https://en.wikipedia.org/wiki/Microsoft_PowerPoint#PowerPoint_Viewer"
    },
    {
      "name": "Reader",
      "qualifier": "document app",
      "birthDate": "2012-10-01",
      "deathDate": "2018-02-16",
      "description": "a freeware program for reading documents in PDF, XPS, and TIFF formats",
      "link": "https://en.wikipedia.org/wiki/Microsoft_Reader"
    },
    {
      "name": "Groove Music Pass",
      "qualifier": "fka Zune Music Pass",
      "birthDate": "2006-11-14",
      "deathDate": "2017-12-31",
      "description": "a music subscription service that allowed streaming of its music catalog to a device",
      "link": "https://en.wikipedia.org/wiki/Groove_Music"
    },
    {
      "name": "CodePlex",
      "birthDate": "2006-05-01",
      "deathDate": "2017-12-15",
      "description": "an open-source developer platform for hosting software project source code, wiki pages, and issue tracking",
      "link": "https://www.zdnet.com/article/microsoft-takes-codeplex-to-death-row-on-back-of-github-monoculture/"
    },
    {
      "name": "Word Viewer",
      "birthDate": "1995-03-20",
      "deathDate": "2017-11-30",
      "description": "a freeware program for Windows that can display and print Microsoft Word documents",
      "link": "https://en.wikipedia.org/wiki/Microsoft_Word_Viewer"
    },
    {
      "name": "WebMatrix",
      "birthDate": "2010-07-07",
      "deathDate": "2017-11-01",
      "description": "a lightweight web development tool with full support for PHP and ASP.NET web pages that succeeded ASP.NET Web Matrix",
      "link": "https://blogs.iis.net/webmatrix/webmatrix-product-support-ends-on-november-1st-2017"
    },
    {
      "name": "Visual J#",
      "birthDate": "2002-07-01",
      "deathDate": "2017-10-10",
      "description": "an implementation of the J# programming language and transitional language for Java developers into the .NET ecosystem",
      "link": "https://en.wikipedia.org/wiki/Visual_J_Sharp"
    },
    {
      "name": "Visual SourceSafe",
      "birthDate": "1994-01-01",
      "deathDate": "2017-07-11",
      "description": "a source control software, originally created by One Tree Software before being acquired by Microsoft",
      "link": "https://en.wikipedia.org/wiki/Microsoft_Visual_SourceSafe"
    },
    {
      "name": "Xbox Fitness",
      "birthDate": "2013-11-22",
      "deathDate": "2017-07-01",
      "description": "a service providing fitness videos and used the Kinect sensor to track player heart rate and calorie burn",
      "link": "https://www.vg247.com/xbox-fitness-is-shutting-down-but-you-still-have-time-to-try-it"
    },
    {
      "name": "So.cl",
      "birthDate": "2012-12-04",
      "deathDate": "2017-05-15",
      "description": "a social networking service and social search engine allowing the posting of collages to be shared with friends or followers",
      "link": "https://en.wikipedia.org/wiki/So.cl"
    },
    {
      "name": "Windows Vista",
      "birthDate": "2007-01-25",
      "deathDate": "2017-04-11",
      "description": "a major release of the Windows NT operating system, succeeding Windows XP",
      "link": "https://en.wikipedia.org/wiki/Windows_Vista"
    },
    {
      "name": "Scalebound",
      "deathDate": "2017-01-09",
      "description": "an unreleased action role-playing game in development by PlatinumGames and to be published by Microsoft before being cancelled",
      "link": "https://www.ign.com/articles/2017/01/09/microsoft-confirms-scalebound-is-cancelled"
    },
    {
      "name": "Lumia",
      "birthDate": "2011-10-26",
      "deathDate": "2016-12-31",
      "description": "a line of mobile devices running Windows Phone operating system originally created by Nokia before being acquired and later abandoned by Microsoft",
      "link": "https://web.archive.org/web/20170509205747/http://hothardware.com/news/microsoft-ends-sales-of-all-lumia-windows-10-mobile-devices-from-microsoft-store"
    },
    {
      "name": "Band",
      "birthDate": "2014-10-30",
      "deathDate": "2016-10-04",
      "description": "a smart band with smartwatch and fitness tracker features",
      "link": "https://www.theverge.com/circuitbreaker/2016/10/3/13152590/microsoft-band-discontinued"
    },
    {
      "name": "Sunrise",
      "birthDate": "2013-02-19",
      "deathDate": "2016-09-13",
      "description": "a calendar application that provided a comprehensive view of daily events before later being acquired by Microsoft and merged into Outlook",
      "link": "https://www.theverge.com/2016/9/1/12746910/microsoft-sunrise-shut-down-delayed"
    },
    {
      "name": "Lionhead Studios",
      "birthDate": "1997-07-01",
      "deathDate": "2016-04-29",
      "description": "a British video game development studio best known for Black & White and Fable series",
      "link": "https://www.polygon.com/2016/3/7/11172408/fable-legends-canceled-lionhead-studios-closing"
    },
    {
      "name": "Xbox 360",
      "birthDate": "2005-11-22",
      "deathDate": "2016-04-20",
      "description": "the second gaming console from Microsoft and competed with the PlayStation 3 and Nintendo Wii in the seventh generation of console gaming hardware",
      "link": "https://news.xbox.com/en-us/2016/04/20/xbox-360-celebrating-10-years/"
    },
    {
      "name": "Fable Legends",
      "deathDate": "2016-04-13",
      "description": "a cancelled 4v1 multiplayer entry in the Fable series before being cancelled and its active beta shutdown before release",
      "link": "https://www.eurogamer.net/articles/2016-03-07-fable-developer-lionhead-studios-to-shut-down"
    },
    {
      "name": "Tay",
      "birthDate": "2016-03-23",
      "deathDate": "2016-03-24",
      "description": "an artificial intelligence chatbot released on Twitter that was shut down after only 16 hours due to inflammatory tweets",
      "link": "https://www.theverge.com/2016/3/24/11297050/tay-microsoft-chatbot-racist"
    },
    {
      "name": "Windows 8",
      "birthDate": "2012-10-30",
      "deathDate": "2016-01-12",
      "description": "a major release of the Windows NT operating system with a touch-optimized experience and based on Metro design language",
      "link": "https://en.wikipedia.org/wiki/Windows_8"
    },
    {
      "name": "FoxPro",
      "qualifier": "fka FoxBASE",
      "birthDate": "1984-12-01",
      "deathDate": "2015-01-13",
      "description": "a data-centric procedural programming language and database management system originally developed by Fox Software before being acquired by Microsoft",
      "link": "http://www.foxprohistory.org/foxprotimeline.htm"
    },
    {
      "name": "Live Messenger",
      "qualifier": "fka MSN Messenger",
      "birthDate": "1999-07-22",
      "deathDate": "2014-10-31",
      "description": "a cross-platform instant-messaging client",
      "link": "https://thenextweb.com/news/microsoft-to-retire-its-messenger-im-service-in-q1-2013-moving-100mm-users-to-skype-in-single-move"
    },
    {
      "name": "Windows XP",
      "birthDate": "2001-08-24",
      "deathDate": "2014-04-08",
      "description": "a major release of the Windows operating system built on Windows NT kernel explicitly for consumer use",
      "link": "https://en.wikipedia.org/wiki/Windows_XP"
    },
    {
      "name": "Reader",
      "qualifier": "e-book app",
      "birthDate": "2000-08-01",
      "deathDate": "2012-08-01",
      "description": "an application for reading e-books and used its own .LIT format",
      "link": "https://web.archive.org/web/20051012094653/http://www.microsoft.com/reader/default.asp"
    },
    {
      "name": "Zune",
      "birthDate": "2006-11-14",
      "deathDate": "2012-06-30",
      "description": "a portable media player turned music software brand",
      "link": "https://appleinsider.com/articles/11/10/04/microsoft_changes_its_story_concedes_death_of_zune_hardware"
    },
    {
      "name": "Kin",
      "birthDate": "2010-04-12",
      "deathDate": "2010-06-30",
      "description": "a short-lived family of mobile devices that heavily integrated social networking services",
      "link": "https://www.engadget.com/2010-06-30-microsoft-kin-is-dead.html"
    },
    {
      "name": "Tafiti",
      "birthDate": "2007-01-01",
      "deathDate": "2009-01-01",
      "description": "an animated search engine that used Silverlight to display search results",
      "link": "https://en.wikipedia.org/wiki/Tafiti"
    },
    {
      "name": "MSJVM",
      "birthDate": "1996-10-13",
      "deathDate": "2007-12-31",
      "description": "a proprietary Java virtual machine from Microsoft",
      "link": "https://web.archive.org/web/20140831134121/https://support.microsoft.com/gp/lifean12"
    },
    {
      "name": "Clippit",
      "qualifier": "aka Clippy",
      "birthDate": "1996-11-19",
      "deathDate": "2007-01-30",
      "description": "the default Office Assistant and currently lives on in spirit as the Windows paperclip emoji",
      "link": "https://en.wikipedia.org/wiki/Office_Assistant"
    },
    {
      "name": "Office Assistant",
      "birthDate": "1996-11-19",
      "deathDate": "2007-01-30",
      "description": "an intelligent user interface for Microsoft Office products",
      "link": "https://en.wikipedia.org/wiki/Office_Assistant"
    },
    {
      "name": "Xbox",
      "qualifier": "original console",
      "birthDate": "2001-11-15",
      "deathDate": "2006-12-31",
      "description": "the first entry into the gaming console market by Microsoft and origin of the Xbox brand",
      "link": "https://en.wikipedia.org/wiki/Xbox_(console)"
    },
    {
      "name": "MSN Music",
      "birthDate": "2004-02-18",
      "deathDate": "2006-11-14",
      "description": "a music download store made to compete with Apple's iTunes Music Store",
      "link": "https://www.neowin.net/news/msn-music-shutting-down-for-zune/"
    },
    {
      "name": "Windows 98",
      "birthDate": "1998-06-25",
      "deathDate": "2006-07-11",
      "description": "a major release of the Windows operating system in 1998, succeeding Windows 95",
      "link": "https://en.wikipedia.org/wiki/Windows_98"
    },
    {
      "name": "Windows Millennium Edition",
      "qualifier": "aka Windows Me",
      "birthDate": "2000-09-14",
      "deathDate": "2006-07-11",
      "description": "a major release of the Windows operating system in 2000, succeeding Windows 98",
      "link": "https://en.wikipedia.org/wiki/Windows_Me"
    },
    {
      "name": "ASP.NET Web Matrix",
      "birthDate": "2002-06-01",
      "deathDate": "2005-11-01",
      "description": "a development tool that was a lightweight alternative to Visual Studio and ideal for web application workloads",
      "link": "https://web.archive.org/web/20100505221027/http://www.asp.net/downloads/archived-v1.1/web-matrix/"
    },
    {
      "name": "Windows 95",
      "birthDate": "1995-08-24",
      "deathDate": "2001-12-31",
      "description": "a major release of the Windows operating system in 1995 and the first of the Windows 9x family",
      "link": "https://en.wikipedia.org/wiki/Windows_95"
    },
    {
      "name": "Bob",
      "birthDate": "1995-03-10",
      "deathDate": "1996-01-01",
      "description": "a Microsoft project intended to provide a personalized alternative interface for the Windows operating system",
      "link": "https://www.youtube.com/watch?v=rXHu9OmLd8Y"
    }
  ]
}
